financeanalytics/dataloader.py
financeanalytics/dataquality.py
financeanalytics/financeanalytics.py
financeanalytics/main.py
financeanalytics/main_gui.py
financeanalytics/statementprocessor.py
finance_analytics-0.0.4.dist-info/LICENSE
finance_analytics-0.0.4.dist-info/METADATA
finance_analytics-0.0.4.dist-info/WHEEL
finance_analytics-0.0.4.dist-info/top_level.txt
finance_analytics-0.0.4.dist-info/RECORD
